flowws_keras_experimental/Classifier.py
flowws_keras_experimental/InitializeTF.py
flowws_keras_experimental/MLP.py
flowws_keras_experimental/PermanentDropout.py
flowws_keras_experimental/Save.py
flowws_keras_experimental/Tensorboard.py
flowws_keras_experimental/Train.py
flowws_keras_experimental/__init__.py
flowws_keras_experimental/accumulate_gradients.py
flowws_keras_experimental/internal.py
flowws_keras_experimental/version.py
flowws_keras_experimental/branch_replicas/Train.py
flowws_keras_experimental/branch_replicas/__init__.py
flowws_keras_experimental/galilean_mc/GalileanModel.py
flowws_keras_experimental/galilean_mc/__init__.py
flowws_keras_experimental/images/CIFAR10.py
flowws_keras_experimental/images/CIFAR100.py
flowws_keras_experimental/images/Encoder.py
flowws_keras_experimental/images/ImagenetDirectory.py
flowws_keras_experimental/images/MNIST.py
flowws_keras_experimental/images/MobileNetV2.py
flowws_keras_experimental/images/ResNet.py
flowws_keras_experimental/images/__init__.py
flowws_keras_experimental/neural_potential/NeuralPotentialController.py
flowws_keras_experimental/neural_potential/NeuralPotentialDropout.py
flowws_keras_experimental/neural_potential/PruneNeuralPotentialLayers.py
flowws_keras_experimental/neural_potential/__init__.py
flowws_keras_experimental/ring_replicas/Train.py
flowws_keras_experimental/text/LSTMLM.py
flowws_keras_experimental/text/TransformerLM.py
flowws_keras_experimental/text/__init__.py
flowws_keras_experimental-0.3.0.dist-info/LICENSE
flowws_keras_experimental-0.3.0.dist-info/METADATA
flowws_keras_experimental-0.3.0.dist-info/WHEEL
flowws_keras_experimental-0.3.0.dist-info/entry_points.txt
flowws_keras_experimental-0.3.0.dist-info/top_level.txt
flowws_keras_experimental-0.3.0.dist-info/RECORD
