Metadata-Version: 2.1
Name: flowws-keras-experimental
Version: 0.3.0
Summary: Stage-based scientific workflows for miscellaneous deep learning experiments
Home-page: UNKNOWN
Author: Matthew Spellings
Author-email: mspells@vectorinstitute.ai
License: MIT
Platform: UNKNOWN
Classifier: Development Status :: 3 - Alpha
Classifier: License :: OSI Approved :: MIT License
Classifier: Programming Language :: Python :: 3
Requires-Python: >=3
License-File: LICENSE
Requires-Dist: flowws
